ecs_ssh/__init__.py
ecs_ssh/ecs_ssh.py
ecs_ssh-1.0.3.dist-info/DESCRIPTION.rst
ecs_ssh-1.0.3.dist-info/METADATA
ecs_ssh-1.0.3.dist-info/RECORD
ecs_ssh-1.0.3.dist-info/WHEEL
ecs_ssh-1.0.3.dist-info/entry_points.txt
ecs_ssh-1.0.3.dist-info/metadata.json
ecs_ssh-1.0.3.dist-info/top_level.txt
